hdfpath/__init__.py
hdfpath/_version.py
hdfpath/hdfpath.py
hdfpath/jsonpath_ng/__init__.py
hdfpath/jsonpath_ng/exceptions.py
hdfpath/jsonpath_ng/jsonpath.py
hdfpath/jsonpath_ng/lexer.py
hdfpath/jsonpath_ng/parser.py
hdfpath/jsonpath_ng/ext/__init__.py
hdfpath/jsonpath_ng/ext/arithmetic.py
hdfpath/jsonpath_ng/ext/filter.py
hdfpath/jsonpath_ng/ext/iterable.py
hdfpath/jsonpath_ng/ext/parser.py
hdfpath/jsonpath_ng/ext/string.py
hdfpath-0.1.0.dist-info/LICENSE
hdfpath-0.1.0.dist-info/METADATA
hdfpath-0.1.0.dist-info/WHEEL
hdfpath-0.1.0.dist-info/top_level.txt
hdfpath-0.1.0.dist-info/zip-safe
hdfpath-0.1.0.dist-info/RECORD
