Metadata-Version: 2.1
Name: hdfpath
Version: 0.1.0
Summary: Quick searches of Hierarchical Data Format (HDF)-Files and dict-like data structures based on JSONPath.
Home-page: https://github.com/mortacious/hdfpath
Author: Felix Igelbrink
Author-email: felix.igelbrink@uni-osnabrueck.de
License: Apache 2.0
Platform: UNKNOWN
Classifier: Development Status :: 4 - Beta
Classifier: Intended Audience :: Developers
Classifier: License :: OSI Approved :: Apache Software License
Classifier: Programming Language :: Python :: 3.6
Classifier: Programming Language :: Python :: 3.7
Classifier: Programming Language :: Python :: 3.8
Classifier: Programming Language :: Python :: 3.9
Requires-Python: >=3.6
License-File: LICENSE
Requires-Dist: ply
Requires-Dist: decorator
Requires-Dist: six
Provides-Extra: hdf5
Requires-Dist: h5py ; extra == 'hdf5'
Provides-Extra: zarr
Requires-Dist: zarr ; extra == 'zarr'
